hinkaponka/__init__.py
hinkaponka/helloworld.py
hinkaponka-0.1.dist-info/LICENSE.txt
hinkaponka-0.1.dist-info/METADATA
hinkaponka-0.1.dist-info/WHEEL
hinkaponka-0.1.dist-info/top_level.txt
hinkaponka-0.1.dist-info/RECORD
