Metadata-Version: 2.1
Name: hinkaponka
Version: 0.1
Summary: Test Helo World package
Home-page: https://github.com/shinjiniray/testpackage
Author: Sayjini Tay
Author-email: shinyan1301@gmail.com
License: MIT
Download-URL: https://pypi.org/project/hinkaponka/
Keywords: Hello,World,HelloWorld
Platform: UNKNOWN
Requires-Dist: numpy
